jyotisha/__init__.py
jyotisha/custom_transliteration.py
jyotisha/nakshatra.py
jyotisha/zodiac.py
jyotisha/names/__init__.py
jyotisha/names/chandra_masa_names.md
jyotisha/names/gen_docs_names.py
jyotisha/names/init_names_auto.py
jyotisha/names/karanam_names.md
jyotisha/names/krishna_ekadashi_names.md
jyotisha/names/masa_names.md
jyotisha/names/nakshatram_names.md
jyotisha/names/rashi_names.md
jyotisha/names/shukla_ekadashi_names.md
jyotisha/names/tithi_names.md
jyotisha/names/vara_names.md
jyotisha/names/year_names.md
jyotisha/names/yogam_names.md
jyotisha/names/data/chandra_masa_names.md
jyotisha/names/data/karanam_names.md
jyotisha/names/data/krishna_ekadashi_names.md
jyotisha/names/data/masa_names.md
jyotisha/names/data/nakshatram_names.md
jyotisha/names/data/rashi_names.md
jyotisha/names/data/shukla_ekadashi_names.md
jyotisha/names/data/tithi_names.md
jyotisha/names/data/translation_table_HK.tsv
jyotisha/names/data/vara_names.md
jyotisha/names/data/year_names.md
jyotisha/names/data/yogam_names.md
jyotisha/panchangam/__init__.py
jyotisha/panchangam/custom_transliteration.py
jyotisha/panchangam/helper_functions.py
jyotisha/panchangam/panchangam.py
jyotisha/panchangam/spatio_temporal.py
jyotisha/panchangam/temporal.py
jyotisha/panchangam/write_daily_panchangam_tex.py
jyotisha/panchangam/write_events_ics.py
jyotisha/panchangam/write_monthly_panchangam_tex.py
jyotisha/panchangam/write_panchangam_ics.py
jyotisha/panchangam/data/__init__.py
jyotisha/panchangam/data/festival_rules.json
jyotisha/panchangam/data/kanchi_aradhana_rules.json
jyotisha/panchangam/data/places_lat_lon_tz.txt
jyotisha/panchangam/data/places_lat_lon_tz_db.txt
jyotisha/panchangam/data/precomputed/Chennai-2016.pickle
jyotisha/panchangam/data/precomputed/Chennai-2017-detailed.pickle
jyotisha/panchangam/data/precomputed/Chennai-2017.pickle
jyotisha/panchangam/data/precomputed/Chennai-2018.pickle
jyotisha-0.0.9.dist-info/DESCRIPTION.rst
jyotisha-0.0.9.dist-info/METADATA
jyotisha-0.0.9.dist-info/RECORD
jyotisha-0.0.9.dist-info/WHEEL
jyotisha-0.0.9.dist-info/metadata.json
jyotisha-0.0.9.dist-info/top_level.txt
