Metadata-Version: 2.0
Name: jyotisha
Version: 0.0.9
Summary: Tools for computations involved in the jyotiSha vedAnga
Home-page: https://github.com/sanskrit-coders/jyotisha
Author: Sanskrit programmers
Author-email: sanskrit-programmers@googlegroups.com
License: MIT
Keywords: indic vedic sanskrit astronomy astrology jyotisa jyotish jyotis,panchanga,panchangam tithi
Platform: UNKNOWN
Classifier: Development Status :: 3 - Alpha
Classifier: Intended Audience :: Education
Classifier: Intended Audience :: Science/Research
Classifier: Intended Audience :: Developers
Classifier: License :: OSI Approved :: MIT License
Classifier: Programming Language :: Python :: 2
Classifier: Programming Language :: Python :: 2.7
Classifier: Programming Language :: Python :: 3
Classifier: Programming Language :: Python :: 3.3
Classifier: Programming Language :: Python :: 3.4
Classifier: Programming Language :: Python :: 3.5
Requires-Dist: icalendar
Requires-Dist: indic-transliteration
Requires-Dist: pandas
Requires-Dist: pyswisseph
Requires-Dist: pytz
Requires-Dist: sanskrit-data
Requires-Dist: scipy
